{"v":"5.7.8","fr":29.9700012207031,"ip":0,"op":71.0000028918893,"w":450,"h":250,"nm":"credit card 1","ddd":0,"assets":[],"fonts":{"list":[{"fName":"OCRAExtended","fFamily":"OCR A Extended","fStyle":"Regular","ascent":64.898681640625}]},"layers":[{"ddd":0,"ind":1,"ty":4,"nm":"Shape Layer 1","td":1,"sr":1,"ks":{"o":{"a":0,"k":100,"ix":11},"r":{"a":0,"k":0,"ix":10},"p":{"a":0,"k":[43,124.538,0],"ix":2,"l":2},"a":{"a":0,"k":[-182,-0.462,0],"ix":1,"l":2},"s":{"a":1,"k":[{"i":{"x":[0.305,0.667,0.667],"y":[1,1,1]},"o":{"x":[0.605,0.333,0.333],"y":[0,0,0]},"t":0,"s":[0,100,100]},{"t":30.0000012219251,"s":[100,100,100]}],"ix":6,"l":2}},"ao":0,"shapes":[{"ty":"gr","it":[{"ty":"rc","d":1,"s":{"a":0,"k":[352,43],"ix":2},"p":{"a":0,"k":[0,0],"ix":3},"r":{"a":0,"k":0,"ix":4},"nm":"Rectangle Path 1","mn":"ADBE Vector Shape - Rect","hd":false},{"ty":"st","c":{"a":0,"k":[0.192156877705,0.192156877705,0.192156877705,1],"ix":3},"o":{"a":0,"k":100,"ix":4},"w":{"a":0,"k":11,"ix":5},"lc":1,"lj":1,"ml":4,"bm":0,"nm":"Stroke 1","mn":"ADBE Vector Graphic - Stroke","hd":false},{"ty":"fl","c":{"a":0,"k":[0,0,0,1],"ix":4},"o":{"a":0,"k":100,"ix":5},"r":1,"bm":0,"nm":"Fill 1","mn":"ADBE Vector Graphic - Fill","hd":false},{"ty":"tr","p":{"a":0,"k":[172,4],"ix":2},"a":{"a":0,"k":[178,1],"ix":1},"s":{"a":0,"k":[100,100],"ix":3},"r":{"a":0,"k":0,"ix":6},"o":{"a":0,"k":100,"ix":7},"sk":{"a":0,"k":0,"ix":4},"sa":{"a":0,"k":0,"ix":5},"nm":"Transform"}],"nm":"Rectangle 1","np":3,"cix":2,"bm":0,"ix":1,"mn":"ADBE Vector Group","hd":false}],"ip":0,"op":71.0000028918893,"st":0,"bm":0},{"ddd":0,"ind":2,"ty":4,"nm":"XXXX XXXX XXX XXXX Outlines","tt":1,"sr":1,"ks":{"o":{"a":0,"k":100,"ix":11},"r":{"a":0,"k":0,"ix":10},"p":{"a":0,"k":[391.581,130.538,0],"ix":2,"l":2},"a":{"a":0,"k":[-2.417,-9.734,0],"ix":1,"l":2},"s":{"a":0,"k":[100,100,100],"ix":6,"l":2}},"ao":0,"shapes":[{"ty":"gr","it":[{"ind":0,"ty":"sh","ix":1,"ks":{"a":0,"k":{"i":[[0,0],[-0.479,0],[-0.239,0.232],[0,0.348],[0.117,0.195],[0,0],[0,0],[0,0.227],[0.255,0.237],[0.342,0],[0.244,-0.408],[0,0],[0,0],[0.477,0],[0.243,-0.239],[0,-0.312],[-0.176,-0.302],[0,0],[0,0],[0,-0.234],[-0.249,-0.254],[-0.352,0],[-0.225,0.391],[0,0]],"o":[[0.234,0.39],[0.342,0],[0.239,-0.232],[0,-0.222],[0,0],[0,0],[0.127,-0.215],[0,-0.335],[-0.255,-0.237],[-0.45,0],[0,0],[0,0],[-0.224,-0.393],[-0.321,0],[-0.244,0.239],[0,0.254],[0,0],[0,0],[-0.147,0.245],[0,0.303],[0.249,0.254],[0.468,0],[0,0],[0,0]],"v":[[-325.555,-0.585],[-324.485,0],[-323.612,-0.348],[-323.253,-1.219],[-323.429,-1.845],[-328.021,-9.725],[-323.4,-17.592],[-323.209,-18.255],[-323.591,-19.113],[-324.486,-19.468],[-325.528,-18.855],[-329.432,-12.222],[-333.397,-18.877],[-334.448,-19.468],[-335.295,-19.109],[-335.66,-18.281],[-335.396,-17.448],[-330.896,-9.737],[-335.484,-1.935],[-335.704,-1.216],[-335.331,-0.381],[-334.431,0],[-333.391,-0.587],[-329.46,-7.277]],"c":true},"ix":2},"nm":"X","mn":"ADBE Vector Shape - Group","hd":false},{"ty":"fl","c":{"a":0,"k":[1,1,1,1],"ix":4},"o":{"a":0,"k":100,"ix":5},"r":1,"bm":0,"nm":"Fill 1","mn":"ADBE Vector Graphic - Fill","hd":false},{"ty":"tr","p":{"a":0,"k":[0,0],"ix":2},"a":{"a":0,"k":[0,0],"ix":1},"s":{"a":0,"k":[100,100],"ix":3},"r":{"a":0,"k":0,"ix":6},"o":{"a":0,"k":100,"ix":7},"sk":{"a":0,"k":0,"ix":4},"sa":{"a":0,"k":0,"ix":5},"nm":"Transform"}],"nm":"X","np":3,"cix":2,"bm":0,"ix":1,"mn":"ADBE Vector Group","hd":false},{"ty":"gr","it":[{"ind":0,"ty":"sh","ix":1,"ks":{"a":0,"k":{"i":[[0,0],[-0.479,0],[-0.239,0.232],[0,0.348],[0.117,0.195],[0,0],[0,0],[0,0.227],[0.255,0.237],[0.342,0],[0.244,-0.408],[0,0],[0,0],[0.477,0],[0.243,-0.239],[0,-0.312],[-0.176,-0.302],[0,0],[0,0],[0,-0.234],[-0.249,-0.254],[-0.352,0],[-0.225,0.391],[0,0]],"o":[[0.234,0.39],[0.342,0],[0.239,-0.232],[0,-0.222],[0,0],[0,0],[0.127,-0.215],[0,-0.335],[-0.255,-0.237],[-0.45,0],[0,0],[0,0],[-0.224,-0.393],[-0.321,0],[-0.244,0.239],[0,0.254],[0,0],[0,0],[-0.147,0.245],[0,0.303],[0.249,0.254],[0.468,0],[0,0],[0,0]],"v":[[-306.685,-0.585],[-305.614,0],[-304.742,-0.348],[-304.383,-1.219],[-304.559,-1.845],[-309.151,-9.725],[-304.53,-17.592],[-304.339,-18.255],[-304.721,-19.113],[-305.616,-19.468],[-306.658,-18.855],[-310.562,-12.222],[-314.527,-18.877],[-315.578,-19.468],[-316.425,-19.109],[-316.79,-18.281],[-316.526,-17.448],[-312.025,-9.737],[-316.614,-1.935],[-316.834,-1.216],[-316.461,-0.381],[-315.56,0],[-314.521,-0.587],[-310.59,-7.277]],"c":true},"ix":2},"nm":"X","mn":"ADBE Vector Shape - Group","hd":false},{"ty":"fl","c":{"a":0,"k":[1,1,1,1],"ix":4},"o":{"a":0,"k":100,"ix":5},"r":1,"bm":0,"nm":"Fill 1","mn":"ADBE Vector Graphic - Fill","hd":false},{"ty":"tr","p":{"a":0,"k":[0,0],"ix":2},"a":{"a":0,"k":[0,0],"ix":1},"s":{"a":0,"k":[100,100],"ix":3},"r":{"a":0,"k":0,"ix":6},"o":{"a":0,"k":100,"ix":7},"sk":{"a":0,"k":0,"ix":4},"sa":{"a":0,"k":0,"ix":5},"nm":"Transform"}],"nm":"X","np":3,"cix":2,"bm":0,"ix":2,"mn":"ADBE Vector Group","hd":false},{"ty":"gr","it":[{"ind":0,"ty":"sh","ix":1,"ks":{"a":0,"k":{"i":[[0,0],[-0.479,0],[-0.239,0.232],[0,0.348],[0.117,0.195],[0,0],[0,0],[0,0.227],[0.255,0.237],[0.342,0],[0.244,-0.408],[0,0],[0,0],[0.477,0],[0.243,-0.239],[0,-0.312],[-0.176,-0.302],[0,0],[0,0],[0,-0.234],[-0.249,-0.254],[-0.352,0],[-0.225,0.391],[0,0]],"o":[[0.234,0.39],[0.342,0],[0.239,-0.232],[0,-0.222],[0,0],[0,0],[0.127,-0.215],[0,-0.335],[-0.255,-0.237],[-0.45,0],[0,0],[0,0],[-0.224,-0.393],[-0.321,0],[-0.244,0.239],[0,0.254],[0,0],[0,0],[-0.147,0.245],[0,0.303],[0.249,0.254],[0.468,0],[0,0],[0,0]],"v":[[-287.815,-0.585],[-286.744,0],[-285.872,-0.348],[-285.513,-1.219],[-285.689,-1.845],[-290.281,-9.725],[-285.659,-17.592],[-285.469,-18.255],[-285.851,-19.113],[-286.746,-19.468],[-287.788,-18.855],[-291.692,-12.222],[-295.657,-18.877],[-296.708,-19.468],[-297.555,-19.109],[-297.92,-18.281],[-297.656,-17.448],[-293.155,-9.737],[-297.744,-1.935],[-297.964,-1.216],[-297.591,-0.381],[-296.69,0],[-295.651,-0.587],[-291.72,-7.277]],"c":true},"ix":2},"nm":"X","mn":"ADBE Vector Shape - Group","hd":false},{"ty":"fl","c":{"a":0,"k":[1,1,1,1],"ix":4},"o":{"a":0,"k":100,"ix":5},"r":1,"bm":0,"nm":"Fill 1","mn":"ADBE Vector Graphic - Fill","hd":false},{"ty":"tr","p":{"a":0,"k":[0,0],"ix":2},"a":{"a":0,"k":[0,0],"ix":1},"s":{"a":0,"k":[100,100],"ix":3},"r":{"a":0,"k":0,"ix":6},"o":{"a":0,"k":100,"ix":7},"sk":{"a":0,"k":0,"ix":4},"sa":{"a":0,"k":0,"ix":5},"nm":"Transform"}],"nm":"X","np":3,"cix":2,"bm":0,"ix":3,"mn":"ADBE Vector Group","hd":false},{"ty":"gr","it":[{"ind":0,"ty":"sh","ix":1,"ks":{"a":0,"k":{"i":[[0,0],[-0.479,0],[-0.239,0.232],[0,0.348],[0.117,0.195],[0,0],[0,0],[0,0.227],[0.255,0.237],[0.342,0],[0.244,-0.408],[0,0],[0,0],[0.477,0],[0.243,-0.239],[0,-0.312],[-0.176,-0.302],[0,0],[0,0],[0,-0.234],[-0.249,-0.254],[-0.352,0],[-0.225,0.391],[0,0]],"o":[[0.234,0.39],[0.342,0],[0.239,-0.232],[0,-0.222],[0,0],[0,0],[0.127,-0.215],[0,-0.335],[-0.255,-0.237],[-0.45,0],[0,0],[0,0],[-0.224,-0.393],[-0.321,0],[-0.244,0.239],[0,0.254],[0,0],[0,0],[-0.147,0.245],[0,0.303],[0.249,0.254],[0.468,0],[0,0],[0,0]],"v":[[-268.944,-0.585],[-267.874,0],[-267.002,-0.348],[-266.643,-1.219],[-266.819,-1.845],[-271.411,-9.725],[-266.789,-17.592],[-266.599,-18.255],[-266.98,-19.113],[-267.876,-19.468],[-268.918,-18.855],[-272.822,-12.222],[-276.787,-18.877],[-277.838,-19.468],[-278.685,-19.109],[-279.05,-18.281],[-278.786,-17.448],[-274.285,-9.737],[-278.874,-1.935],[-279.094,-1.216],[-278.721,-0.381],[-277.82,0],[-276.781,-0.587],[-272.85,-7.277]],"c":true},"ix":2},"nm":"X","mn":"ADBE Vector Shape - Group","hd":false},{"ty":"fl","c":{"a":0,"k":[1,1,1,1],"ix":4},"o":{"a":0,"k":100,"ix":5},"r":1,"bm":0,"nm":"Fill 1","mn":"ADBE Vector Graphic - Fill","hd":false},{"ty":"tr","p":{"a":0,"k":[0,0],"ix":2},"a":{"a":0,"k":[0,0],"ix":1},"s":{"a":0,"k":[100,100],"ix":3},"r":{"a":0,"k":0,"ix":6},"o":{"a":0,"k":100,"ix":7},"sk":{"a":0,"k":0,"ix":4},"sa":{"a":0,"k":0,"ix":5},"nm":"Transform"}],"nm":"X","np":3,"cix":2,"bm":0,"ix":4,"mn":"ADBE Vector Group","hd":false},{"ty":"gr","it":[{"ind":0,"ty":"sh","ix":1,"ks":{"a":0,"k":{"i":[[0,0],[-0.479,0],[-0.239,0.232],[0,0.348],[0.117,0.195],[0,0],[0,0],[0,0.227],[0.255,0.237],[0.342,0],[0.244,-0.408],[0,0],[0,0],[0.477,0],[0.243,-0.239],[0,-0.312],[-0.176,-0.302],[0,0],[0,0],[0,-0.234],[-0.249,-0.254],[-0.352,0],[-0.225,0.391],[0,0]],"o":[[0.234,0.39],[0.342,0],[0.239,-0.232],[0,-0.222],[0,0],[0,0],[0.127,-0.215],[0,-0.335],[-0.255,-0.237],[-0.45,0],[0,0],[0,0],[-0.224,-0.393],[-0.321,0],[-0.244,0.239],[0,0.254],[0,0],[0,0],[-0.147,0.245],[0,0.303],[0.249,0.254],[0.468,0],[0,0],[0,0]],"v":[[-231.204,-0.585],[-230.134,0],[-229.262,-0.348],[-228.902,-1.219],[-229.078,-1.845],[-233.671,-9.725],[-229.049,-17.592],[-228.858,-18.255],[-229.24,-19.113],[-230.136,-19.468],[-231.178,-18.855],[-235.082,-12.222],[-239.046,-18.877],[-240.098,-19.468],[-240.945,-19.109],[-241.31,-18.281],[-241.046,-17.448],[-236.545,-9.737],[-241.134,-1.935],[-241.354,-1.216],[-240.98,-0.381],[-240.08,0],[-239.041,-0.587],[-235.11,-7.277]],"c":true},"ix":2},"nm":"X","mn":"ADBE Vector Shape - Group","hd":false},{"ty":"fl","c":{"a":0,"k":[1,1,1,1],"ix":4},"o":{"a":0,"k":100,"ix":5},"r":1,"bm":0,"nm":"Fill 1","mn":"ADBE Vector Graphic - Fill","hd":false},{"ty":"tr","p":{"a":0,"k":[0,0],"ix":2},"a":{"a":0,"k":[0,0],"ix":1},"s":{"a":0,"k":[100,100],"ix":3},"r":{"a":0,"k":0,"ix":6},"o":{"a":0,"k":100,"ix":7},"sk":{"a":0,"k":0,"ix":4},"sa":{"a":0,"k":0,"ix":5},"nm":"Transform"}],"nm":"X","np":3,"cix":2,"bm":0,"ix":5,"mn":"ADBE Vector Group","hd":false},{"ty":"gr","it":[{"ind":0,"ty":"sh","ix":1,"ks":{"a":0,"k":{"i":[[0,0],[-0.479,0],[-0.239,0.232],[0,0.348],[0.117,0.195],[0,0],[0,0],[0,0.227],[0.255,0.237],[0.342,0],[0.244,-0.408],[0,0],[0,0],[0.477,0],[0.243,-0.239],[0,-0.312],[-0.176,-0.302],[0,0],[0,0],[0,-0.234],[-0.249,-0.254],[-0.352,0],[-0.225,0.391],[0,0]],"o":[[0.234,0.39],[0.342,0],[0.239,-0.232],[0,-0.222],[0,0],[0,0],[0.127,-0.215],[0,-0.335],[-0.255,-0.237],[-0.45,0],[0,0],[0,0],[-0.224,-0.393],[-0.321,0],[-0.244,0.239],[0,0.254],[0,0],[0,0],[-0.147,0.245],[0,0.303],[0.249,0.254],[0.468,0],[0,0],[0,0]],"v":[[-212.334,-0.585],[-211.264,0],[-210.392,-0.348],[-210.032,-1.219],[-210.208,-1.845],[-214.801,-9.725],[-210.179,-17.592],[-209.988,-18.255],[-210.37,-19.113],[-211.265,-19.468],[-212.308,-18.855],[-216.212,-12.222],[-220.176,-18.877],[-221.228,-19.468],[-222.074,-19.109],[-222.439,-18.281],[-222.176,-17.448],[-217.675,-9.737],[-222.263,-1.935],[-222.483,-1.216],[-222.11,-0.381],[-221.21,0],[-220.171,-0.587],[-216.24,-7.277]],"c":true},"ix":2},"nm":"X","mn":"ADBE Vector Shape - Group","hd":false},{"ty":"fl","c":{"a":0,"k":[1,1,1,1],"ix":4},"o":{"a":0,"k":100,"ix":5},"r":1,"bm":0,"nm":"Fill 1","mn":"ADBE Vector Graphic - Fill","hd":false},{"ty":"tr","p":{"a":0,"k":[0,0],"ix":2},"a":{"a":0,"k":[0,0],"ix":1},"s":{"a":0,"k":[100,100],"ix":3},"r":{"a":0,"k":0,"ix":6},"o":{"a":0,"k":100,"ix":7},"sk":{"a":0,"k":0,"ix":4},"sa":{"a":0,"k":0,"ix":5},"nm":"Transform"}],"nm":"X","np":3,"cix":2,"bm":0,"ix":6,"mn":"ADBE Vector Group","hd":false},{"ty":"gr","it":[{"ind":0,"ty":"sh","ix":1,"ks":{"a":0,"k":{"i":[[0,0],[-0.479,0],[-0.239,0.232],[0,0.348],[0.117,0.195],[0,0],[0,0],[0,0.227],[0.255,0.237],[0.342,0],[0.244,-0.408],[0,0],[0,0],[0.477,0],[0.243,-0.239],[0,-0.312],[-0.176,-0.302],[0,0],[0,0],[0,-0.234],[-0.249,-0.254],[-0.352,0],[-0.225,0.391],[0,0]],"o":[[0.234,0.39],[0.342,0],[0.239,-0.232],[0,-0.222],[0,0],[0,0],[0.127,-0.215],[0,-0.335],[-0.255,-0.237],[-0.45,0],[0,0],[0,0],[-0.224,-0.393],[-0.321,0],[-0.244,0.239],[0,0.254],[0,0],[0,0],[-0.147,0.245],[0,0.303],[0.249,0.254],[0.468,0],[0,0],[0,0]],"v":[[-193.464,-0.585],[-192.394,0],[-191.521,-0.348],[-191.162,-1.219],[-191.338,-1.845],[-195.931,-9.725],[-191.309,-17.592],[-191.118,-18.255],[-191.5,-19.113],[-192.395,-19.468],[-193.437,-18.855],[-197.342,-12.222],[-201.306,-18.877],[-202.357,-19.468],[-203.204,-19.109],[-203.569,-18.281],[-203.305,-17.448],[-198.805,-9.737],[-203.393,-1.935],[-203.613,-1.216],[-203.24,-0.381],[-202.34,0],[-201.301,-0.587],[-197.37,-7.277]],"c":true},"ix":2},"nm":"X","mn":"ADBE Vector Shape - Group","hd":false},{"ty":"fl","c":{"a":0,"k":[1,1,1,1],"ix":4},"o":{"a":0,"k":100,"ix":5},"r":1,"bm":0,"nm":"Fill 1","mn":"ADBE Vector Graphic - Fill","hd":false},{"ty":"tr","p":{"a":0,"k":[0,0],"ix":2},"a":{"a":0,"k":[0,0],"ix":1},"s":{"a":0,"k":[100,100],"ix":3},"r":{"a":0,"k":0,"ix":6},"o":{"a":0,"k":100,"ix":7},"sk":{"a":0,"k":0,"ix":4},"sa":{"a":0,"k":0,"ix":5},"nm":"Transform"}],"nm":"X","np":3,"cix":2,"bm":0,"ix":7,"mn":"ADBE Vector Group","hd":false},{"ty":"gr","it":[{"ind":0,"ty":"sh","ix":1,"ks":{"a":0,"k":{"i":[[0,0],[-0.479,0],[-0.239,0.232],[0,0.348],[0.117,0.195],[0,0],[0,0],[0,0.227],[0.255,0.237],[0.342,0],[0.244,-0.408],[0,0],[0,0],[0.477,0],[0.243,-0.239],[0,-0.312],[-0.176,-0.302],[0,0],[0,0],[0,-0.234],[-0.249,-0.254],[-0.352,0],[-0.225,0.391],[0,0]],"o":[[0.234,0.39],[0.342,0],[0.239,-0.232],[0,-0.222],[0,0],[0,0],[0.127,-0.215],[0,-0.335],[-0.255,-0.237],[-0.45,0],[0,0],[0,0],[-0.224,-0.393],[-0.321,0],[-0.244,0.239],[0,0.254],[0,0],[0,0],[-0.147,0.245],[0,0.303],[0.249,0.254],[0.468,0],[0,0],[0,0]],"v":[[-174.594,-0.585],[-173.524,0],[-172.651,-0.348],[-172.292,-1.219],[-172.468,-1.845],[-177.061,-9.725],[-172.439,-17.592],[-172.248,-18.255],[-172.63,-19.113],[-173.525,-19.468],[-174.567,-18.855],[-178.472,-12.222],[-182.436,-18.877],[-183.487,-19.468],[-184.334,-19.109],[-184.699,-18.281],[-184.435,-17.448],[-179.935,-9.737],[-184.523,-1.935],[-184.743,-1.216],[-184.37,-0.381],[-183.47,0],[-182.431,-0.587],[-178.499,-7.277]],"c":true},"ix":2},"nm":"X","mn":"ADBE Vector Shape - Group","hd":false},{"ty":"fl","c":{"a":0,"k":[1,1,1,1],"ix":4},"o":{"a":0,"k":100,"ix":5},"r":1,"bm":0,"nm":"Fill 1","mn":"ADBE Vector Graphic - Fill","hd":false},{"ty":"tr","p":{"a":0,"k":[0,0],"ix":2},"a":{"a":0,"k":[0,0],"ix":1},"s":{"a":0,"k":[100,100],"ix":3},"r":{"a":0,"k":0,"ix":6},"o":{"a":0,"k":100,"ix":7},"sk":{"a":0,"k":0,"ix":4},"sa":{"a":0,"k":0,"ix":5},"nm":"Transform"}],"nm":"X","np":3,"cix":2,"bm":0,"ix":8,"mn":"ADBE Vector Group","hd":false},{"ty":"gr","it":[{"ind":0,"ty":"sh","ix":1,"ks":{"a":0,"k":{"i":[[0,0],[-0.479,0],[-0.239,0.232],[0,0.348],[0.117,0.195],[0,0],[0,0],[0,0.227],[0.255,0.237],[0.342,0],[0.244,-0.408],[0,0],[0,0],[0.477,0],[0.243,-0.239],[0,-0.312],[-0.176,-0.302],[0,0],[0,0],[0,-0.234],[-0.249,-0.254],[-0.352,0],[-0.225,0.391],[0,0]],"o":[[0.234,0.39],[0.342,0],[0.239,-0.232],[0,-0.222],[0,0],[0,0],[0.127,-0.215],[0,-0.335],[-0.255,-0.237],[-0.45,0],[0,0],[0,0],[-0.224,-0.393],[-0.321,0],[-0.244,0.239],[0,0.254],[0,0],[0,0],[-0.147,0.245],[0,0.303],[0.249,0.254],[0.468,0],[0,0],[0,0]],"v":[[-136.854,-0.585],[-135.783,0],[-134.911,-0.348],[-134.552,-1.219],[-134.728,-1.845],[-139.32,-9.725],[-134.698,-17.592],[-134.508,-18.255],[-134.89,-19.113],[-135.785,-19.468],[-136.827,-18.855],[-140.731,-12.222],[-144.696,-18.877],[-145.747,-19.468],[-146.594,-19.109],[-146.959,-18.281],[-146.695,-17.448],[-142.194,-9.737],[-146.783,-1.935],[-147.003,-1.216],[-146.63,-0.381],[-145.729,0],[-144.69,-0.587],[-140.759,-7.277]],"c":true},"ix":2},"nm":"X","mn":"ADBE Vector Shape - Group","hd":false},{"ty":"fl","c":{"a":0,"k":[1,1,1,1],"ix":4},"o":{"a":0,"k":100,"ix":5},"r":1,"bm":0,"nm":"Fill 1","mn":"ADBE Vector Graphic - Fill","hd":false},{"ty":"tr","p":{"a":0,"k":[0,0],"ix":2},"a":{"a":0,"k":[0,0],"ix":1},"s":{"a":0,"k":[100,100],"ix":3},"r":{"a":0,"k":0,"ix":6},"o":{"a":0,"k":100,"ix":7},"sk":{"a":0,"k":0,"ix":4},"sa":{"a":0,"k":0,"ix":5},"nm":"Transform"}],"nm":"X","np":3,"cix":2,"bm":0,"ix":9,"mn":"ADBE Vector Group","hd":false},{"ty":"gr","it":[{"ind":0,"ty":"sh","ix":1,"ks":{"a":0,"k":{"i":[[0,0],[-0.479,0],[-0.239,0.232],[0,0.348],[0.117,0.195],[0,0],[0,0],[0,0.227],[0.255,0.237],[0.342,0],[0.244,-0.408],[0,0],[0,0],[0.477,0],[0.243,-0.239],[0,-0.312],[-0.176,-0.302],[0,0],[0,0],[0,-0.234],[-0.249,-0.254],[-0.352,0],[-0.225,0.391],[0,0]],"o":[[0.234,0.39],[0.342,0],[0.239,-0.232],[0,-0.222],[0,0],[0,0],[0.127,-0.215],[0,-0.335],[-0.255,-0.237],[-0.45,0],[0,0],[0,0],[-0.224,-0.393],[-0.321,0],[-0.244,0.239],[0,0.254],[0,0],[0,0],[-0.147,0.245],[0,0.303],[0.249,0.254],[0.468,0],[0,0],[0,0]],"v":[[-117.984,-0.585],[-116.913,0],[-116.041,-0.348],[-115.682,-1.219],[-115.858,-1.845],[-120.45,-9.725],[-115.828,-17.592],[-115.638,-18.255],[-116.019,-19.113],[-116.915,-19.468],[-117.957,-18.855],[-121.861,-12.222],[-125.826,-18.877],[-126.877,-19.468],[-127.724,-19.109],[-128.089,-18.281],[-127.825,-17.448],[-123.324,-9.737],[-127.913,-1.935],[-128.133,-1.216],[-127.76,-0.381],[-126.859,0],[-125.82,-0.587],[-121.889,-7.277]],"c":true},"ix":2},"nm":"X","mn":"ADBE Vector Shape - Group","hd":false},{"ty":"fl","c":{"a":0,"k":[1,1,1,1],"ix":4},"o":{"a":0,"k":100,"ix":5},"r":1,"bm":0,"nm":"Fill 1","mn":"ADBE Vector Graphic - Fill","hd":false},{"ty":"tr","p":{"a":0,"k":[0,0],"ix":2},"a":{"a":0,"k":[0,0],"ix":1},"s":{"a":0,"k":[100,100],"ix":3},"r":{"a":0,"k":0,"ix":6},"o":{"a":0,"k":100,"ix":7},"sk":{"a":0,"k":0,"ix":4},"sa":{"a":0,"k":0,"ix":5},"nm":"Transform"}],"nm":"X","np":3,"cix":2,"bm":0,"ix":10,"mn":"ADBE Vector Group","hd":false},{"ty":"gr","it":[{"ind":0,"ty":"sh","ix":1,"ks":{"a":0,"k":{"i":[[0,0],[-0.479,0],[-0.239,0.232],[0,0.348],[0.117,0.195],[0,0],[0,0],[0,0.227],[0.255,0.237],[0.342,0],[0.244,-0.408],[0,0],[0,0],[0.477,0],[0.243,-0.239],[0,-0.312],[-0.176,-0.302],[0,0],[0,0],[0,-0.234],[-0.249,-0.254],[-0.352,0],[-0.225,0.391],[0,0]],"o":[[0.234,0.39],[0.342,0],[0.239,-0.232],[0,-0.222],[0,0],[0,0],[0.127,-0.215],[0,-0.335],[-0.255,-0.237],[-0.45,0],[0,0],[0,0],[-0.224,-0.393],[-0.321,0],[-0.244,0.239],[0,0.254],[0,0],[0,0],[-0.147,0.245],[0,0.303],[0.249,0.254],[0.468,0],[0,0],[0,0]],"v":[[-99.113,-0.585],[-98.043,0],[-97.171,-0.348],[-96.812,-1.219],[-96.988,-1.845],[-101.58,-9.725],[-96.958,-17.592],[-96.768,-18.255],[-97.149,-19.113],[-98.045,-19.468],[-99.087,-18.855],[-102.991,-12.222],[-106.956,-18.877],[-108.007,-19.468],[-108.854,-19.109],[-109.219,-18.281],[-108.955,-17.448],[-104.454,-9.737],[-109.043,-1.935],[-109.263,-1.216],[-108.89,-0.381],[-107.989,0],[-106.95,-0.587],[-103.019,-7.277]],"c":true},"ix":2},"nm":"X","mn":"ADBE Vector Shape - Group","hd":false},{"ty":"fl","c":{"a":0,"k":[1,1,1,1],"ix":4},"o":{"a":0,"k":100,"ix":5},"r":1,"bm":0,"nm":"Fill 1","mn":"ADBE Vector Graphic - Fill","hd":false},{"ty":"tr","p":{"a":0,"k":[0,0],"ix":2},"a":{"a":0,"k":[0,0],"ix":1},"s":{"a":0,"k":[100,100],"ix":3},"r":{"a":0,"k":0,"ix":6},"o":{"a":0,"k":100,"ix":7},"sk":{"a":0,"k":0,"ix":4},"sa":{"a":0,"k":0,"ix":5},"nm":"Transform"}],"nm":"X","np":3,"cix":2,"bm":0,"ix":11,"mn":"ADBE Vector Group","hd":false},{"ty":"gr","it":[{"ind":0,"ty":"sh","ix":1,"ks":{"a":0,"k":{"i":[[0,0],[-0.479,0],[-0.239,0.232],[0,0.348],[0.117,0.195],[0,0],[0,0],[0,0.227],[0.255,0.237],[0.342,0],[0.244,-0.408],[0,0],[0,0],[0.477,0],[0.243,-0.239],[0,-0.312],[-0.176,-0.302],[0,0],[0,0],[0,-0.234],[-0.249,-0.254],[-0.352,0],[-0.225,0.391],[0,0]],"o":[[0.234,0.39],[0.342,0],[0.239,-0.232],[0,-0.222],[0,0],[0,0],[0.127,-0.215],[0,-0.335],[-0.255,-0.237],[-0.45,0],[0,0],[0,0],[-0.224,-0.393],[-0.321,0],[-0.244,0.239],[0,0.254],[0,0],[0,0],[-0.147,0.245],[0,0.303],[0.249,0.254],[0.468,0],[0,0],[0,0]],"v":[[-61.373,-0.585],[-60.303,0],[-59.431,-0.348],[-59.071,-1.219],[-59.247,-1.845],[-63.84,-9.725],[-59.218,-17.592],[-59.027,-18.255],[-59.409,-19.113],[-60.305,-19.468],[-61.347,-18.855],[-65.251,-12.222],[-69.215,-18.877],[-70.267,-19.468],[-71.113,-19.109],[-71.479,-18.281],[-71.215,-17.448],[-66.714,-9.737],[-71.303,-1.935],[-71.522,-1.216],[-71.149,-0.381],[-70.249,0],[-69.21,-0.587],[-65.279,-7.277]],"c":true},"ix":2},"nm":"X","mn":"ADBE Vector Shape - Group","hd":false},{"ty":"fl","c":{"a":0,"k":[1,1,1,1],"ix":4},"o":{"a":0,"k":100,"ix":5},"r":1,"bm":0,"nm":"Fill 1","mn":"ADBE Vector Graphic - Fill","hd":false},{"ty":"tr","p":{"a":0,"k":[0,0],"ix":2},"a":{"a":0,"k":[0,0],"ix":1},"s":{"a":0,"k":[100,100],"ix":3},"r":{"a":0,"k":0,"ix":6},"o":{"a":0,"k":100,"ix":7},"sk":{"a":0,"k":0,"ix":4},"sa":{"a":0,"k":0,"ix":5},"nm":"Transform"}],"nm":"X","np":3,"cix":2,"bm":0,"ix":12,"mn":"ADBE Vector Group","hd":false},{"ty":"gr","it":[{"ind":0,"ty":"sh","ix":1,"ks":{"a":0,"k":{"i":[[0,0],[-0.479,0],[-0.239,0.232],[0,0.348],[0.117,0.195],[0,0],[0,0],[0,0.227],[0.255,0.237],[0.342,0],[0.244,-0.408],[0,0],[0,0],[0.477,0],[0.243,-0.239],[0,-0.312],[-0.176,-0.302],[0,0],[0,0],[0,-0.234],[-0.249,-0.254],[-0.352,0],[-0.225,0.391],[0,0]],"o":[[0.234,0.39],[0.342,0],[0.239,-0.232],[0,-0.222],[0,0],[0,0],[0.127,-0.215],[0,-0.335],[-0.255,-0.237],[-0.45,0],[0,0],[0,0],[-0.224,-0.393],[-0.321,0],[-0.244,0.239],[0,0.254],[0,0],[0,0],[-0.147,0.245],[0,0.303],[0.249,0.254],[0.468,0],[0,0],[0,0]],"v":[[-42.503,-0.585],[-41.433,0],[-40.561,-0.348],[-40.201,-1.219],[-40.377,-1.845],[-44.97,-9.725],[-40.348,-17.592],[-40.157,-18.255],[-40.539,-19.113],[-41.434,-19.468],[-42.476,-18.855],[-46.381,-12.222],[-50.345,-18.877],[-51.396,-19.468],[-52.243,-19.109],[-52.608,-18.281],[-52.344,-17.448],[-47.844,-9.737],[-52.432,-1.935],[-52.652,-1.216],[-52.279,-0.381],[-51.379,0],[-50.34,-0.587],[-46.409,-7.277]],"c":true},"ix":2},"nm":"X","mn":"ADBE Vector Shape - Group","hd":false},{"ty":"fl","c":{"a":0,"k":[1,1,1,1],"ix":4},"o":{"a":0,"k":100,"ix":5},"r":1,"bm":0,"nm":"Fill 1","mn":"ADBE Vector Graphic - Fill","hd":false},{"ty":"tr","p":{"a":0,"k":[0,0],"ix":2},"a":{"a":0,"k":[0,0],"ix":1},"s":{"a":0,"k":[100,100],"ix":3},"r":{"a":0,"k":0,"ix":6},"o":{"a":0,"k":100,"ix":7},"sk":{"a":0,"k":0,"ix":4},"sa":{"a":0,"k":0,"ix":5},"nm":"Transform"}],"nm":"X","np":3,"cix":2,"bm":0,"ix":13,"mn":"ADBE Vector Group","hd":false},{"ty":"gr","it":[{"ind":0,"ty":"sh","ix":1,"ks":{"a":0,"k":{"i":[[0,0],[-0.479,0],[-0.239,0.232],[0,0.348],[0.117,0.195],[0,0],[0,0],[0,0.227],[0.255,0.237],[0.342,0],[0.244,-0.408],[0,0],[0,0],[0.477,0],[0.243,-0.239],[0,-0.312],[-0.176,-0.302],[0,0],[0,0],[0,-0.234],[-0.249,-0.254],[-0.352,0],[-0.225,0.391],[0,0]],"o":[[0.234,0.39],[0.342,0],[0.239,-0.232],[0,-0.222],[0,0],[0,0],[0.127,-0.215],[0,-0.335],[-0.255,-0.237],[-0.45,0],[0,0],[0,0],[-0.224,-0.393],[-0.321,0],[-0.244,0.239],[0,0.254],[0,0],[0,0],[-0.147,0.245],[0,0.303],[0.249,0.254],[0.468,0],[0,0],[0,0]],"v":[[-23.633,-0.585],[-22.563,0],[-21.69,-0.348],[-21.331,-1.219],[-21.507,-1.845],[-26.1,-9.725],[-21.478,-17.592],[-21.287,-18.255],[-21.669,-19.113],[-22.564,-19.468],[-23.606,-18.855],[-27.511,-12.222],[-31.475,-18.877],[-32.526,-19.468],[-33.373,-19.109],[-33.738,-18.281],[-33.474,-17.448],[-28.974,-9.737],[-33.562,-1.935],[-33.782,-1.216],[-33.409,-0.381],[-32.509,0],[-31.47,-0.587],[-27.539,-7.277]],"c":true},"ix":2},"nm":"X","mn":"ADBE Vector Shape - Group","hd":false},{"ty":"fl","c":{"a":0,"k":[1,1,1,1],"ix":4},"o":{"a":0,"k":100,"ix":5},"r":1,"bm":0,"nm":"Fill 1","mn":"ADBE Vector Graphic - Fill","hd":false},{"ty":"tr","p":{"a":0,"k":[0,0],"ix":2},"a":{"a":0,"k":[0,0],"ix":1},"s":{"a":0,"k":[100,100],"ix":3},"r":{"a":0,"k":0,"ix":6},"o":{"a":0,"k":100,"ix":7},"sk":{"a":0,"k":0,"ix":4},"sa":{"a":0,"k":0,"ix":5},"nm":"Transform"}],"nm":"X","np":3,"cix":2,"bm":0,"ix":14,"mn":"ADBE Vector Group","hd":false},{"ty":"gr","it":[{"ind":0,"ty":"sh","ix":1,"ks":{"a":0,"k":{"i":[[0,0],[-0.479,0],[-0.239,0.232],[0,0.348],[0.117,0.195],[0,0],[0,0],[0,0.227],[0.255,0.237],[0.342,0],[0.244,-0.408],[0,0],[0,0],[0.477,0],[0.243,-0.239],[0,-0.312],[-0.176,-0.302],[0,0],[0,0],[0,-0.234],[-0.249,-0.254],[-0.352,0],[-0.225,0.391],[0,0]],"o":[[0.234,0.39],[0.342,0],[0.239,-0.232],[0,-0.222],[0,0],[0,0],[0.127,-0.215],[0,-0.335],[-0.255,-0.237],[-0.45,0],[0,0],[0,0],[-0.224,-0.393],[-0.321,0],[-0.244,0.239],[0,0.254],[0,0],[0,0],[-0.147,0.245],[0,0.303],[0.249,0.254],[0.468,0],[0,0],[0,0]],"v":[[-4.763,-0.585],[-3.693,0],[-2.82,-0.348],[-2.461,-1.219],[-2.637,-1.845],[-7.229,-9.725],[-2.608,-17.592],[-2.417,-18.255],[-2.799,-19.113],[-3.694,-19.468],[-4.736,-18.855],[-8.641,-12.222],[-12.605,-18.877],[-13.656,-19.468],[-14.503,-19.109],[-14.868,-18.281],[-14.604,-17.448],[-10.104,-9.737],[-14.692,-1.935],[-14.912,-1.216],[-14.539,-0.381],[-13.639,0],[-12.599,-0.587],[-8.668,-7.277]],"c":true},"ix":2},"nm":"X","mn":"ADBE Vector Shape - Group","hd":false},{"ty":"fl","c":{"a":0,"k":[1,1,1,1],"ix":4},"o":{"a":0,"k":100,"ix":5},"r":1,"bm":0,"nm":"Fill 1","mn":"ADBE Vector Graphic - Fill","hd":false},{"ty":"tr","p":{"a":0,"k":[0,0],"ix":2},"a":{"a":0,"k":[0,0],"ix":1},"s":{"a":0,"k":[100,100],"ix":3},"r":{"a":0,"k":0,"ix":6},"o":{"a":0,"k":100,"ix":7},"sk":{"a":0,"k":0,"ix":4},"sa":{"a":0,"k":0,"ix":5},"nm":"Transform"}],"nm":"X","np":3,"cix":2,"bm":0,"ix":15,"mn":"ADBE Vector Group","hd":false}],"ip":0,"op":71.0000028918893,"st":0,"bm":0},{"ddd":0,"ind":4,"ty":5,"nm":"VALID THRU","sr":1,"ks":{"o":{"a":0,"k":100,"ix":11},"r":{"a":0,"k":0,"ix":10},"p":{"a":0,"k":[422,216,0],"ix":2,"l":2},"a":{"a":0,"k":[0,0,0],"ix":1,"l":2},"s":{"a":0,"k":[100,100,100],"ix":6,"l":2}},"ao":0,"t":{"d":{"k":[{"s":{"s":18,"f":"OCRAExtended","t":"VALID THRU","ca":0,"j":1,"tr":25,"lh":21.6,"ls":0,"fc":[1,1,1]},"t":0}]},"p":{},"m":{"g":1,"a":{"a":0,"k":[0,0],"ix":2}},"a":[]},"ip":0,"op":71.0000028918893,"st":0,"bm":0},{"ddd":0,"ind":5,"ty":5,"nm":"CARDHOLDER NAME","sr":1,"ks":{"o":{"a":0,"k":100,"ix":11},"r":{"a":0,"k":0,"ix":10},"p":{"a":0,"k":[193,216,0],"ix":2,"l":2},"a":{"a":0,"k":[0,0,0],"ix":1,"l":2},"s":{"a":0,"k":[100,100,100],"ix":6,"l":2}},"ao":0,"t":{"d":{"k":[{"s":{"s":18,"f":"OCRAExtended","t":"CARDHOLDER NAME","ca":0,"j":1,"tr":25,"lh":21.6,"ls":0,"fc":[1,1,1]},"t":0}]},"p":{},"m":{"g":1,"a":{"a":0,"k":[0,0],"ix":2}},"a":[]},"ip":0,"op":71.0000028918893,"st":0,"bm":0},{"ddd":0,"ind":8,"ty":4,"nm":"mask 2","td":1,"sr":1,"ks":{"o":{"a":0,"k":100,"ix":11},"r":{"a":0,"k":0,"ix":10},"p":{"a":0,"k":[226.438,125,0],"ix":2,"l":2},"a":{"a":0,"k":[0,0,0],"ix":1,"l":2},"s":{"a":0,"k":[100,100,100],"ix":6,"l":2}},"ao":0,"shapes":[{"ty":"gr","it":[{"ty":"rc","d":1,"s":{"a":0,"k":[441,231],"ix":2},"p":{"a":0,"k":[0,0],"ix":3},"r":{"a":0,"k":20,"ix":4},"nm":"Rectangle Path 1","mn":"ADBE Vector Shape - Rect","hd":false},{"ty":"gf","o":{"a":0,"k":100,"ix":10},"r":1,"bm":0,"g":{"p":3,"k":{"a":0,"k":[0,0.965,0.431,0.557,0.5,0.69,0.414,0.751,1,0.416,0.396,0.945],"ix":9}},"s":{"a":0,"k":[-210,0],"ix":5},"e":{"a":0,"k":[196,0],"ix":6},"t":1,"nm":"Gradient Fill 1","mn":"ADBE Vector Graphic - G-Fill","hd":false},{"ty":"tr","p":{"a":0,"k":[-1.5,-1.5],"ix":2},"a":{"a":0,"k":[0,0],"ix":1},"s":{"a":0,"k":[100,100],"ix":3},"r":{"a":0,"k":0,"ix":6},"o":{"a":0,"k":100,"ix":7},"sk":{"a":0,"k":0,"ix":4},"sa":{"a":0,"k":0,"ix":5},"nm":"Transform"}],"nm":"Rectangle 1","np":3,"cix":2,"bm":0,"ix":1,"mn":"ADBE Vector Group","hd":false}],"ip":0,"op":71.0000028918893,"st":0,"bm":0},{"ddd":0,"ind":9,"ty":4,"nm":"brightness layer 2","tt":1,"sr":1,"ks":{"o":{"a":1,"k":[{"i":{"x":[0.833],"y":[0.833]},"o":{"x":[0.167],"y":[0.167]},"t":30,"s":[25]},{"i":{"x":[0.833],"y":[0.833]},"o":{"x":[0.167],"y":[0.167]},"t":36,"s":[57]},{"i":{"x":[0.833],"y":[0.833]},"o":{"x":[0.167],"y":[0.167]},"t":45,"s":[57]},{"t":50.0000020365418,"s":[25]}],"ix":11},"r":{"a":0,"k":-65,"ix":10},"p":{"a":1,"k":[{"i":{"x":0.271,"y":1},"o":{"x":0.37,"y":0},"t":33,"s":[60.005,125,0],"to":[0,0,0],"ti":[0,0,0]},{"t":55.0000022401959,"s":[638,125,0]}],"ix":2,"l":2},"a":{"a":0,"k":[0,0,0],"ix":1,"l":2},"s":{"a":0,"k":[100,109.961,100],"ix":6,"l":2}},"ao":0,"ef":[{"ty":29,"nm":"Gaussian Blur","np":5,"mn":"ADBE Gaussian Blur 2","ix":1,"en":1,"ef":[{"ty":0,"nm":"Blurriness","mn":"ADBE Gaussian Blur 2-0001","ix":1,"v":{"a":0,"k":61.1,"ix":1}},{"ty":7,"nm":"Blur Dimensions","mn":"ADBE Gaussian Blur 2-0002","ix":2,"v":{"a":0,"k":1,"ix":2}},{"ty":7,"nm":"Repeat Edge Pixels","mn":"ADBE Gaussian Blur 2-0003","ix":3,"v":{"a":0,"k":0,"ix":3}}]}],"shapes":[{"ty":"gr","it":[{"ty":"rc","d":1,"s":{"a":0,"k":[458,40],"ix":2},"p":{"a":0,"k":[0,0],"ix":3},"r":{"a":0,"k":0,"ix":4},"nm":"Rectangle Path 1","mn":"ADBE Vector Shape - Rect","hd":false},{"ty":"gf","o":{"a":0,"k":100,"ix":10},"r":1,"bm":0,"g":{"p":5,"k":{"a":0,"k":[0,1,1,1,0.257,1,1,1,0.515,1,1,1,0.757,1,1,1,1,1,1,1,0,0.7,0.259,0.85,0.517,1,0.759,0.75,1,0.5],"ix":9}},"s":{"a":0,"k":[-211,6],"ix":5},"e":{"a":0,"k":[200,0],"ix":6},"t":1,"nm":"Gradient Fill 1","mn":"ADBE Vector Graphic - G-Fill","hd":false},{"ty":"tr","p":{"a":0,"k":[8,-102.5],"ix":2},"a":{"a":0,"k":[0,0],"ix":1},"s":{"a":0,"k":[100,51.173],"ix":3},"r":{"a":0,"k":0,"ix":6},"o":{"a":0,"k":100,"ix":7},"sk":{"a":0,"k":0,"ix":4},"sa":{"a":0,"k":0,"ix":5},"nm":"Transform"}],"nm":"Rectangle 1","np":3,"cix":2,"bm":0,"ix":1,"mn":"ADBE Vector Group","hd":false}],"ip":33.0000013441176,"op":104.000004236007,"st":33.0000013441176,"bm":0},{"ddd":0,"ind":10,"ty":4,"nm":"mask","td":1,"sr":1,"ks":{"o":{"a":0,"k":100,"ix":11},"r":{"a":0,"k":0,"ix":10},"p":{"a":0,"k":[226.438,125,0],"ix":2,"l":2},"a":{"a":0,"k":[0,0,0],"ix":1,"l":2},"s":{"a":0,"k":[100,100,100],"ix":6,"l":2}},"ao":0,"shapes":[{"ty":"gr","it":[{"ty":"rc","d":1,"s":{"a":0,"k":[441,231],"ix":2},"p":{"a":0,"k":[0,0],"ix":3},"r":{"a":0,"k":20,"ix":4},"nm":"Rectangle Path 1","mn":"ADBE Vector Shape - Rect","hd":false},{"ty":"gf","o":{"a":0,"k":100,"ix":10},"r":1,"bm":0,"g":{"p":3,"k":{"a":0,"k":[0,0.965,0.431,0.557,0.5,0.69,0.414,0.751,1,0.416,0.396,0.945],"ix":9}},"s":{"a":0,"k":[-210,0],"ix":5},"e":{"a":0,"k":[196,0],"ix":6},"t":1,"nm":"Gradient Fill 1","mn":"ADBE Vector Graphic - G-Fill","hd":false},{"ty":"tr","p":{"a":0,"k":[-1.5,-1.5],"ix":2},"a":{"a":0,"k":[0,0],"ix":1},"s":{"a":0,"k":[100,100],"ix":3},"r":{"a":0,"k":0,"ix":6},"o":{"a":0,"k":100,"ix":7},"sk":{"a":0,"k":0,"ix":4},"sa":{"a":0,"k":0,"ix":5},"nm":"Transform"}],"nm":"Rectangle 1","np":3,"cix":2,"bm":0,"ix":1,"mn":"ADBE Vector Group","hd":false}],"ip":0,"op":71.0000028918893,"st":0,"bm":0},{"ddd":0,"ind":11,"ty":4,"nm":"brightness layer","tt":1,"sr":1,"ks":{"o":{"a":1,"k":[{"i":{"x":[0.833],"y":[0.833]},"o":{"x":[0.167],"y":[0.167]},"t":30,"s":[24]},{"i":{"x":[0.833],"y":[0.833]},"o":{"x":[0.167],"y":[0.167]},"t":36,"s":[57]},{"i":{"x":[0.833],"y":[0.833]},"o":{"x":[0.167],"y":[0.167]},"t":45,"s":[57]},{"t":50.0000020365418,"s":[24]}],"ix":11},"r":{"a":0,"k":-65,"ix":10},"p":{"a":1,"k":[{"i":{"x":0.299,"y":1},"o":{"x":0.363,"y":0},"t":30,"s":[35,125,0],"to":[0,0,0],"ti":[0,0,0]},{"t":53.0000021587343,"s":[715,125,0]}],"ix":2,"l":2},"a":{"a":0,"k":[0,0,0],"ix":1,"l":2},"s":{"a":0,"k":[100,100,100],"ix":6,"l":2}},"ao":0,"ef":[{"ty":29,"nm":"Gaussian Blur","np":5,"mn":"ADBE Gaussian Blur 2","ix":1,"en":1,"ef":[{"ty":0,"nm":"Blurriness","mn":"ADBE Gaussian Blur 2-0001","ix":1,"v":{"a":0,"k":61.1,"ix":1}},{"ty":7,"nm":"Blur Dimensions","mn":"ADBE Gaussian Blur 2-0002","ix":2,"v":{"a":0,"k":1,"ix":2}},{"ty":7,"nm":"Repeat Edge Pixels","mn":"ADBE Gaussian Blur 2-0003","ix":3,"v":{"a":0,"k":0,"ix":3}}]}],"shapes":[{"ty":"gr","it":[{"ty":"rc","d":1,"s":{"a":0,"k":[458,40],"ix":2},"p":{"a":0,"k":[0,0],"ix":3},"r":{"a":0,"k":0,"ix":4},"nm":"Rectangle Path 1","mn":"ADBE Vector Shape - Rect","hd":false},{"ty":"gf","o":{"a":0,"k":100,"ix":10},"r":1,"bm":0,"g":{"p":5,"k":{"a":0,"k":[0,1,1,1,0.257,1,1,1,0.515,1,1,1,0.757,1,1,1,1,1,1,1,0,0.7,0.259,0.85,0.517,1,0.759,0.75,1,0.5],"ix":9}},"s":{"a":0,"k":[-211,6],"ix":5},"e":{"a":0,"k":[200,0],"ix":6},"t":1,"nm":"Gradient Fill 1","mn":"ADBE Vector Graphic - G-Fill","hd":false},{"ty":"tr","p":{"a":0,"k":[8,-102.5],"ix":2},"a":{"a":0,"k":[0,0],"ix":1},"s":{"a":0,"k":[100,171.321],"ix":3},"r":{"a":0,"k":0,"ix":6},"o":{"a":0,"k":100,"ix":7},"sk":{"a":0,"k":0,"ix":4},"sa":{"a":0,"k":0,"ix":5},"nm":"Transform"}],"nm":"Rectangle 1","np":3,"cix":2,"bm":0,"ix":1,"mn":"ADBE Vector Group","hd":false}],"ip":30.0000012219251,"op":101.000004113814,"st":30.0000012219251,"bm":0},{"ddd":0,"ind":12,"ty":4,"nm":"Shape Layer 2","sr":1,"ks":{"o":{"a":0,"k":100,"ix":11},"r":{"a":0,"k":0,"ix":10},"p":{"a":0,"k":[193,140,0],"ix":2,"l":2},"a":{"a":0,"k":[0,0,0],"ix":1,"l":2},"s":{"a":0,"k":[124,124,100],"ix":6,"l":2}},"ao":0,"shapes":[{"ty":"gr","it":[{"d":1,"ty":"el","s":{"a":0,"k":[42,42],"ix":2},"p":{"a":0,"k":[0,0],"ix":3},"nm":"Ellipse Path 1","mn":"ADBE Vector Shape - Ellipse","hd":false},{"ty":"st","c":{"a":0,"k":[0.447058853449,0.396078461292,0.929411824544,1],"ix":3},"o":{"a":0,"k":100,"ix":4},"w":{"a":0,"k":5,"ix":5},"lc":1,"lj":1,"ml":4,"bm":0,"nm":"Stroke 1","mn":"ADBE Vector Graphic - Stroke","hd":false},{"ty":"gf","o":{"a":0,"k":100,"ix":10},"r":1,"bm":0,"g":{"p":3,"k":{"a":0,"k":[0,1,1,1,0.5,0.859,0.804,1,1,0.718,0.608,1],"ix":9}},"s":{"a":0,"k":[-14,-13],"ix":5},"e":{"a":0,"k":[14,15],"ix":6},"t":1,"nm":"Gradient Fill 1","mn":"ADBE Vector Graphic - G-Fill","hd":false},{"ty":"tr","p":{"a":0,"k":[166.5,-68],"ix":2},"a":{"a":0,"k":[0,0],"ix":1},"s":{"a":0,"k":[100,100],"ix":3},"r":{"a":0,"k":0,"ix":6},"o":{"a":0,"k":100,"ix":7},"sk":{"a":0,"k":0,"ix":4},"sa":{"a":0,"k":0,"ix":5},"nm":"Transform"}],"nm":"Ellipse 1","np":3,"cix":2,"bm":0,"ix":1,"mn":"ADBE Vector Group","hd":false},{"ty":"gr","it":[{"d":1,"ty":"el","s":{"a":0,"k":[37,37],"ix":2},"p":{"a":0,"k":[0,0],"ix":3},"nm":"Ellipse Path 1","mn":"ADBE Vector Shape - Ellipse","hd":false},{"ty":"gf","o":{"a":0,"k":100,"ix":10},"r":1,"bm":0,"g":{"p":3,"k":{"a":0,"k":[0,0.979,0.965,1,0.5,0.862,0.804,1,1,0.745,0.643,1],"ix":9}},"s":{"a":0,"k":[-14.5,-13.75],"ix":5},"e":{"a":0,"k":[8.5,15.25],"ix":6},"t":1,"nm":"Gradient Fill 1","mn":"ADBE Vector Graphic - G-Fill","hd":false},{"ty":"tr","p":{"a":0,"k":[137,-68],"ix":2},"a":{"a":0,"k":[0,0],"ix":1},"s":{"a":0,"k":[100,100],"ix":3},"r":{"a":0,"k":0,"ix":6},"o":{"a":0,"k":100,"ix":7},"sk":{"a":0,"k":0,"ix":4},"sa":{"a":0,"k":0,"ix":5},"nm":"Transform"}],"nm":"Ellipse 2","np":3,"cix":2,"bm":0,"ix":2,"mn":"ADBE Vector Group","hd":false}],"ip":0,"op":71.0000028918893,"st":0,"bm":0},{"ddd":0,"ind":14,"ty":4,"nm":"Shape Layer 3","sr":1,"ks":{"o":{"a":0,"k":100,"ix":11},"r":{"a":0,"k":0,"ix":10},"p":{"a":0,"k":[226.438,125,0],"ix":2,"l":2},"a":{"a":0,"k":[0,0,0],"ix":1,"l":2},"s":{"a":0,"k":[100,100,100],"ix":6,"l":2}},"ao":0,"shapes":[{"ty":"gr","it":[{"ty":"rc","d":1,"s":{"a":0,"k":[441,231],"ix":2},"p":{"a":0,"k":[0,0],"ix":3},"r":{"a":0,"k":20,"ix":4},"nm":"Rectangle Path 1","mn":"ADBE Vector Shape - Rect","hd":false},{"ty":"gf","o":{"a":0,"k":100,"ix":10},"r":1,"bm":0,"g":{"p":3,"k":{"a":0,"k":[0,0.965,0.431,0.557,0.5,0.69,0.414,0.751,1,0.416,0.396,0.945],"ix":9}},"s":{"a":0,"k":[-210,0],"ix":5},"e":{"a":0,"k":[196,0],"ix":6},"t":1,"nm":"Gradient Fill 1","mn":"ADBE Vector Graphic - G-Fill","hd":false},{"ty":"tr","p":{"a":0,"k":[-1.5,-1.5],"ix":2},"a":{"a":0,"k":[0,0],"ix":1},"s":{"a":0,"k":[100,100],"ix":3},"r":{"a":0,"k":0,"ix":6},"o":{"a":0,"k":100,"ix":7},"sk":{"a":0,"k":0,"ix":4},"sa":{"a":0,"k":0,"ix":5},"nm":"Transform"}],"nm":"Rectangle 1","np":3,"cix":2,"bm":0,"ix":1,"mn":"ADBE Vector Group","hd":false}],"ip":0,"op":71.0000028918893,"st":0,"bm":0}],"markers":[],"chars":[{"ch":"C","size":18,"style":"Regular","w":60.4,"data":{"shapes":[{"ty":"gr","it":[{"ind":0,"ty":"sh","ix":1,"ks":{"a":0,"k":{"i":[[0.813,1.726],[0,0],[-0.005,1.924],[-0.718,1.334],[0,0],[-1.302,0.004],[0,0],[-0.797,0.83],[0,1.14],[0.797,0.814],[1.139,0],[0,0],[1.92,-1.286],[0.911,-1.692],[0,0],[0,-3.059],[-1.27,-2.637],[0,0],[-2.084,-1.237],[-1.953,0],[0,0],[-0.83,0.798],[0,1.14],[0.83,0.798],[1.14,0],[0,0]],"o":[[0,0],[-0.781,-1.465],[-0.007,-1.826],[0,0],[0.815,-1.529],[0,0],[1.138,0],[0.797,-0.83],[0,-1.106],[-0.798,-0.813],[0,0],[-1.791,0],[-1.921,1.286],[0,0],[-1.205,2.246],[0,2.767],[0,0],[0.813,1.53],[2.083,1.237],[0,0],[1.139,0],[0.83,-0.797],[0,-1.139],[-0.831,-0.797],[0,0],[-1.857,0.005]],"v":[[28.6,-10.784],[19.914,-27.486],[18.75,-32.569],[19.817,-37.309],[28.915,-54.293],[32.09,-56.592],[47.707,-56.592],[50.611,-57.837],[51.807,-60.791],[50.61,-63.672],[47.705,-64.893],[31.494,-64.893],[25.928,-62.964],[21.68,-58.496],[12.109,-40.381],[10.303,-32.422],[12.207,-24.316],[21.68,-6.006],[26.025,-1.855],[32.08,0],[47.412,0],[50.366,-1.196],[51.611,-4.102],[50.365,-7.007],[47.409,-8.203],[32.604,-8.203]],"c":true},"ix":2},"nm":"C","mn":"ADBE Vector Shape - Group","hd":false}],"nm":"C","np":3,"cix":2,"bm":0,"ix":1,"mn":"ADBE Vector Group","hd":false}]},"fFamily":"OCR A Extended"},{"ch":"A","size":18,"style":"Regular","w":60.4,"data":{"shapes":[{"ty":"gr","it":[{"ind":0,"ty":"sh","ix":1,"ks":{"a":0,"k":{"i":[[0,-0.488],[-0.786,-0.813],[-1.211,0],[-0.72,0.47],[-0.098,0.519],[0,0],[0,0],[0,0],[-2.148,0],[-0.781,0.798],[0,1.14],[0.13,0.423],[0,0],[2.04,0],[0.658,-2.033],[0,0]],"o":[[0,1.172],[0.785,0.814],[0.851,0],[0.719,-0.469],[0,0],[0,0],[0,0],[0.585,1.987],[1.009,0],[0.781,-0.797],[0,-0.391],[0,0],[-0.526,-1.724],[-2.107,0],[0,0],[-0.162,0.522]],"v":[[10.107,-4.199],[11.285,-1.221],[14.279,0],[16.635,-0.704],[17.862,-2.186],[21.435,-14.111],[40.218,-14.111],[43.461,-2.979],[47.56,0],[50.244,-1.196],[51.416,-4.102],[51.221,-5.322],[34.865,-62.305],[31.014,-64.893],[26.867,-61.842],[10.35,-5.714]],"c":true},"ix":2},"nm":"A","mn":"ADBE Vector Shape - Group","hd":false},{"ind":1,"ty":"sh","ix":2,"ks":{"a":0,"k":{"i":[[0,0],[0,0],[0,0]],"o":[[0,0],[0,0],[0,0]],"v":[[37.799,-22.412],[23.921,-22.412],[30.957,-45.898]],"c":true},"ix":2},"nm":"A","mn":"ADBE Vector Shape - Group","hd":false}],"nm":"A","np":5,"cix":2,"bm":0,"ix":1,"mn":"ADBE Vector Group","hd":false}]},"fFamily":"OCR A Extended"},{"ch":"R","size":18,"style":"Regular","w":60.4,"data":{"shapes":[{"ty":"gr","it":[{"ind":0,"ty":"sh","ix":1,"ks":{"a":0,"k":{"i":[[-0.798,-0.797],[-1.14,0],[-0.83,0.798],[0,1.14],[0,0],[0,0],[0,0],[-1.633,0.008],[-0.849,0.798],[0,1.107],[0.519,0.847],[0,0],[0,0],[-2.409,2.425],[0,3.418],[0,0],[2.425,2.441],[3.352,0],[0,0],[0,0]],"o":[[0.797,0.798],[1.139,0],[0.83,-0.797],[0,0],[0,0],[0,0],[0.842,1.466],[1.077,0],[0.848,-0.797],[0,-0.846],[0,0],[0,0],[3.385,0],[2.409,-2.425],[0,0],[0,-3.385],[-2.425,-2.441],[0,0],[0,0],[0,1.14]],"v":[[11.401,-1.196],[14.307,0],[17.261,-1.196],[18.506,-4.102],[18.506,-35.4],[24.432,-35.4],[43.638,-2.187],[47.351,0],[50.24,-1.196],[51.514,-4.053],[50.735,-6.592],[33.984,-35.4],[39.209,-35.4],[47.9,-39.038],[51.514,-47.803],[51.514,-52.49],[47.876,-61.23],[39.209,-64.893],[10.205,-64.893],[10.205,-4.102]],"c":true},"ix":2},"nm":"R","mn":"ADBE Vector Shape - Group","hd":false},{"ind":1,"ty":"sh","ix":2,"ks":{"a":0,"k":{"i":[[0,0],[0,0],[-0.798,-0.797],[0,-1.139],[0,0],[0.797,-0.797],[1.139,0],[0,0]],"o":[[0,0],[1.139,0],[0.797,0.798],[0,0],[0,1.14],[-0.798,0.798],[0,0],[0,0]],"v":[[18.408,-56.592],[39.209,-56.592],[42.114,-55.396],[43.311,-52.49],[43.311,-47.705],[42.114,-44.8],[39.209,-43.604],[18.408,-43.604]],"c":true},"ix":2},"nm":"R","mn":"ADBE Vector Shape - Group","hd":false}],"nm":"R","np":5,"cix":2,"bm":0,"ix":1,"mn":"ADBE Vector Group","hd":false}]},"fFamily":"OCR A Extended"},{"ch":"D","size":18,"style":"Regular","w":60.4,"data":{"shapes":[{"ty":"gr","it":[{"ind":0,"ty":"sh","ix":1,"ks":{"a":0,"k":{"i":[[0.797,-0.813],[0,-1.106],[-0.798,-0.83],[-1.14,0],[0,0],[0,0],[0,0],[0.797,-0.83],[0,-1.139],[-0.798,-0.813],[-1.14,0],[0,0],[-1.953,1.254],[-1.042,2.084],[0,0],[0,2.995],[1.53,2.962],[0,0],[2.002,1.335],[2.116,0.033],[0,0]],"o":[[-0.798,0.814],[0,1.14],[0.797,0.83],[0,0],[0,0],[0,0],[-1.14,0],[-0.798,0.83],[0,1.107],[0.797,0.814],[0,0],[2.409,0],[1.953,-1.253],[0,0],[1.627,-3.157],[0,-3.223],[0,0],[-0.945,-1.888],[-2.002,-1.334],[0,0],[-1.14,0]],"v":[[11.206,-63.672],[10.01,-60.791],[11.206,-57.837],[14.111,-56.592],[18.311,-56.592],[18.311,-8.301],[14.014,-8.301],[11.108,-7.056],[9.912,-4.102],[11.108,-1.221],[14.014,0],[29.688,0],[36.23,-1.88],[40.723,-6.885],[48.877,-23.096],[51.318,-32.324],[49.023,-41.602],[40.918,-58.008],[36.499,-62.842],[30.322,-64.893],[14.111,-64.893]],"c":true},"ix":2},"nm":"D","mn":"ADBE Vector Shape - Group","hd":false},{"ind":1,"ty":"sh","ix":2,"ks":{"a":0,"k":{"i":[[0,0],[-0.879,-1.66],[0,0],[-0.002,-1.787],[1.009,-2.116],[0,0],[1.817,0],[0,0],[0,0]],"o":[[1.987,-0.001],[0,0],[0.813,1.595],[-0.012,1.43],[0,0],[-0.912,1.791],[0,0],[0,0],[0,0]],"v":[[29.201,-56.592],[33.498,-54.103],[41.894,-37.402],[43.115,-32.329],[41.583,-27.011],[33.477,-10.899],[29.385,-8.213],[26.514,-8.203],[26.514,-56.592]],"c":true},"ix":2},"nm":"D","mn":"ADBE Vector Shape - Group","hd":false}],"nm":"D","np":5,"cix":2,"bm":0,"ix":1,"mn":"ADBE Vector Group","hd":false}]},"fFamily":"OCR A Extended"},{"ch":"H","size":18,"style":"Regular","w":60.4,"data":{"shapes":[{"ty":"gr","it":[{"ind":0,"ty":"sh","ix":1,"ks":{"a":0,"k":{"i":[[-0.814,-0.797],[-1.107,0],[-0.83,0.814],[0,1.107],[0,0],[0,0],[0,0],[-0.781,-0.797],[-1.172,0],[-0.83,0.814],[0,1.107],[0,0],[0.797,0.814],[1.139,0],[0.797,-0.813],[0,-1.106],[0,0],[0,0],[0,0],[0.813,0.814],[1.106,0],[0.797,-0.813],[0,-1.106],[0,0]],"o":[[0.813,0.798],[1.139,0],[0.83,-0.813],[0,0],[0,0],[0,0],[0,1.14],[0.781,0.798],[1.074,0],[0.83,-0.813],[0,0],[0,-1.172],[-0.798,-0.813],[-1.14,0],[-0.798,0.814],[0,0],[0,0],[0,0],[0,-1.106],[-0.814,-0.813],[-1.14,0],[-0.798,0.814],[0,0],[0,1.14]],"v":[[11.133,-1.196],[14.014,0],[16.968,-1.221],[18.213,-4.102],[18.213,-28.418],[43.115,-28.418],[43.115,-4.102],[44.287,-1.196],[47.217,0],[50.073,-1.221],[51.318,-4.102],[51.318,-60.693],[50.122,-63.672],[47.217,-64.893],[44.312,-63.672],[43.115,-60.791],[43.115,-36.621],[18.115,-36.621],[18.115,-60.791],[16.895,-63.672],[14.014,-64.893],[11.108,-63.672],[9.912,-60.791],[9.912,-4.102]],"c":true},"ix":2},"nm":"H","mn":"ADBE Vector Shape - Group","hd":false}],"nm":"H","np":3,"cix":2,"bm":0,"ix":1,"mn":"ADBE Vector Group","hd":false}]},"fFamily":"OCR A Extended"},{"ch":"O","size":18,"style":"Regular","w":60.4,"data":{"shapes":[{"ty":"gr","it":[{"ind":0,"ty":"sh","ix":1,"ks":{"a":0,"k":{"i":[[4.557,0],[2.051,-4.004],[0,0],[0,-3.027],[-1.205,-2.376],[0,0],[-1.742,-1.139],[-2.181,0],[-1.921,4.004],[0,0],[0,2.865],[1.27,2.507],[0,0]],"o":[[-4.492,0],[0,0],[-1.205,2.409],[0,3.027],[0,0],[0.879,1.726],[1.741,1.14],[4.59,0],[0,0],[1.27,-2.539],[0,-2.93],[0,0],[-1.953,-4.004]],"v":[[30.713,-64.893],[20.898,-58.887],[11.816,-40.479],[10.01,-32.324],[11.816,-24.219],[20.898,-6.006],[24.829,-1.709],[30.713,0],[40.479,-6.006],[49.512,-24.219],[51.416,-32.324],[49.512,-40.479],[40.479,-58.887]],"c":true},"ix":2},"nm":"O","mn":"ADBE Vector Shape - Group","hd":false},{"ind":1,"ty":"sh","ix":2,"ks":{"a":0,"k":{"i":[[-1.172,0],[-0.554,-1.27],[0,0],[0,-1.79],[0.813,-1.725],[0,0],[1.041,0],[0.455,1.074],[0,0],[0,1.791],[-0.781,1.726],[0,0]],"o":[[1.172,0],[0,0],[0.813,1.595],[0,1.693],[0,0],[-0.554,1.074],[-1.205,0],[0,0],[-0.781,-1.627],[0,-1.66],[0,0],[0.651,-1.27]],"v":[[30.713,-56.689],[33.301,-54.785],[41.895,-37.5],[43.115,-32.422],[41.895,-27.295],[33.105,-9.814],[30.713,-8.203],[28.223,-9.814],[19.482,-27.295],[18.311,-32.422],[19.482,-37.5],[27.979,-54.785]],"c":true},"ix":2},"nm":"O","mn":"ADBE Vector Shape - Group","hd":false}],"nm":"O","np":5,"cix":2,"bm":0,"ix":1,"mn":"ADBE Vector Group","hd":false}]},"fFamily":"OCR A Extended"},{"ch":"L","size":18,"style":"Regular","w":60.4,"data":{"shapes":[{"ty":"gr","it":[{"ind":0,"ty":"sh","ix":1,"ks":{"a":0,"k":{"i":[[0,0],[-0.83,0.798],[0,1.14],[0.83,0.798],[1.139,0],[0,0],[0,0],[0.813,0.814],[1.106,0],[0.813,-0.813],[0,-1.106],[0,0]],"o":[[1.139,0],[0.83,-0.797],[0,-1.139],[-0.83,-0.797],[0,0],[0,0],[0,-1.106],[-0.814,-0.813],[-1.107,0],[-0.814,0.814],[0,0],[0,0]],"v":[[47.314,0],[50.269,-1.196],[51.514,-4.102],[50.269,-7.007],[47.314,-8.203],[18.311,-8.203],[18.311,-60.791],[17.09,-63.672],[14.209,-64.893],[11.328,-63.672],[10.107,-60.791],[10.107,0]],"c":true},"ix":2},"nm":"L","mn":"ADBE Vector Shape - Group","hd":false}],"nm":"L","np":3,"cix":2,"bm":0,"ix":1,"mn":"ADBE Vector Group","hd":false}]},"fFamily":"OCR A Extended"},{"ch":"E","size":18,"style":"Regular","w":60.4,"data":{"shapes":[{"ty":"gr","it":[{"ind":0,"ty":"sh","ix":1,"ks":{"a":0,"k":{"i":[[-0.83,0.814],[0,1.107],[0.83,0.83],[1.139,0],[0,0],[0,0],[0,0],[-0.83,0.798],[0,1.14],[0.813,0.798],[1.106,0],[0,0],[0,0],[0,0],[-0.798,0.814],[0,1.172],[0.813,0.814],[1.106,0],[0,0],[0,0],[0,0]],"o":[[0.83,-0.813],[0,-1.139],[-0.83,-0.83],[0,0],[0,0],[0,0],[1.139,0],[0.83,-0.797],[0,-1.139],[-0.814,-0.797],[0,0],[0,0],[0,0],[1.139,0],[0.797,-0.813],[0,-1.106],[-0.814,-0.813],[0,0],[0,0],[0,0],[1.139,0]],"v":[[50.269,-57.813],[51.514,-60.693],[50.269,-63.647],[47.314,-64.893],[10.107,-64.893],[10.107,0],[47.314,0],[50.269,-1.196],[51.514,-4.102],[50.293,-7.007],[47.412,-8.203],[18.311,-8.203],[18.311,-28.32],[30.811,-28.32],[33.716,-29.541],[34.912,-32.52],[33.691,-35.4],[30.811,-36.621],[18.311,-36.621],[18.311,-56.592],[47.314,-56.592]],"c":true},"ix":2},"nm":"E","mn":"ADBE Vector Shape - Group","hd":false}],"nm":"E","np":3,"cix":2,"bm":0,"ix":1,"mn":"ADBE Vector Group","hd":false}]},"fFamily":"OCR A Extended"},{"ch":" ","size":18,"style":"Regular","w":60.4,"data":{},"fFamily":"OCR A Extended"},{"ch":"N","size":18,"style":"Regular","w":60.4,"data":{"shapes":[{"ty":"gr","it":[{"ind":0,"ty":"sh","ix":1,"ks":{"a":0,"k":{"i":[[0.797,0.814],[1.139,0],[0.83,-0.83],[0,-1.139],[0,0],[0,0],[0,0],[0,0],[-0.798,-0.797],[-1.14,0],[-0.798,0.798],[0,1.14],[0,0],[0,0],[0,0],[0,0]],"o":[[-0.798,-0.813],[-1.14,0],[-0.83,0.83],[0,0],[0,0],[0,0],[0,0],[0,1.14],[0.797,0.798],[1.139,0],[0.797,-0.797],[0,0],[0,0],[0,0],[0,0],[0,-1.172]],"v":[[50.22,-63.672],[47.314,-64.893],[44.36,-63.647],[43.115,-60.693],[43.115,-14.6],[20.946,-64.893],[10.107,-64.893],[10.107,-4.102],[11.304,-1.196],[14.209,0],[17.114,-1.196],[18.311,-4.102],[18.311,-50.391],[40.415,0],[51.416,0],[51.416,-60.693]],"c":true},"ix":2},"nm":"N","mn":"ADBE Vector Shape - Group","hd":false}],"nm":"N","np":3,"cix":2,"bm":0,"ix":1,"mn":"ADBE Vector Group","hd":false}]},"fFamily":"OCR A Extended"},{"ch":"M","size":18,"style":"Regular","w":60.4,"data":{"shapes":[{"ty":"gr","it":[{"ind":0,"ty":"sh","ix":1,"ks":{"a":0,"k":{"i":[[-0.798,-0.813],[-1.14,0],[-0.814,0.814],[0,1.107],[0,0],[0,0],[0,0],[-0.814,-0.813],[-1.107,0],[-0.83,0.798],[0,1.14],[0,0],[0,0],[0,0],[0,0],[0,0],[0,0],[-0.798,-0.813],[-1.14,0],[-0.798,0.798],[0,1.14],[0,0],[0,0],[0,0]],"o":[[0.797,0.814],[1.106,0],[0.813,-0.813],[0,0],[0,0],[0,0],[0,1.107],[0.813,0.814],[1.139,0],[0.83,-0.797],[0,0],[0,0],[0,0],[0,0],[0,0],[0,0],[0,1.107],[0.797,0.814],[1.139,0],[0.797,-0.797],[0,0],[0,0],[0,0],[0,1.107]],"v":[[27.808,-36.523],[30.713,-35.303],[33.594,-36.523],[34.814,-39.404],[34.814,-41.699],[43.115,-53.418],[43.115,-4.102],[44.336,-1.221],[47.217,0],[50.171,-1.196],[51.416,-4.102],[51.416,-64.893],[41.01,-64.893],[30.597,-50.191],[20.52,-64.893],[9.912,-64.893],[9.912,-4.102],[11.108,-1.221],[14.014,0],[16.919,-1.196],[18.115,-4.102],[18.115,-53.613],[26.611,-41.504],[26.611,-39.404]],"c":true},"ix":2},"nm":"M","mn":"ADBE Vector Shape - Group","hd":false}],"nm":"M","np":3,"cix":2,"bm":0,"ix":1,"mn":"ADBE Vector Group","hd":false}]},"fFamily":"OCR A Extended"},{"ch":"V","size":18,"style":"Regular","w":60.4,"data":{"shapes":[{"ty":"gr","it":[{"ind":0,"ty":"sh","ix":1,"ks":{"a":0,"k":{"i":[[0.8,0.814],[1.141,0],[0.8,-0.813],[0,-1.171],[0,0],[0,0],[0,0],[0,0],[0.799,0.813],[1.141,0],[0.799,-0.813],[0,-1.172],[0,0],[0,0],[-1.917,0],[-0.845,2.055],[0,0],[0,0]],"o":[[-0.8,-0.813],[-1.143,0],[-0.8,0.813],[0,0],[0,0],[0,0],[0,0],[0,-1.171],[-0.8,-0.813],[-1.142,0],[-0.8,0.814],[0,0],[0,0],[0.812,2.051],[1.819,0],[0,0],[0,0],[0,-1.172]],"v":[[50.412,-63.672],[47.5,-64.893],[44.587,-63.673],[43.388,-60.696],[43.388,-47.225],[30.908,-15.479],[18.425,-47.321],[18.425,-60.695],[17.226,-63.672],[14.315,-64.893],[11.404,-63.672],[10.205,-60.693],[10.205,-45.605],[26.807,-3.076],[30.9,0],[34.895,-3.083],[51.611,-45.605],[51.611,-60.693]],"c":true},"ix":2},"nm":"V","mn":"ADBE Vector Shape - Group","hd":false}],"nm":"V","np":3,"cix":2,"bm":0,"ix":1,"mn":"ADBE Vector Group","hd":false}]},"fFamily":"OCR A Extended"},{"ch":"I","size":18,"style":"Regular","w":60.4,"data":{"shapes":[{"ty":"gr","it":[{"ind":0,"ty":"sh","ix":1,"ks":{"a":0,"k":{"i":[[0.797,-0.813],[0,-1.172],[-0.798,-0.813],[-1.14,0],[0,0],[0,0],[0,0],[0.797,-0.797],[0,-1.139],[-0.798,-0.797],[-1.14,0],[0,0],[-0.814,0.798],[0,1.14],[0.797,0.798],[1.139,0],[0,0],[0,0],[0,0],[-0.814,0.83],[0,1.14],[0.83,0.814],[1.074,0],[0,0]],"o":[[-0.798,0.814],[0,1.107],[0.797,0.814],[0,0],[0,0],[0,0],[-1.14,0],[-0.798,0.798],[0,1.14],[0.797,0.798],[0,0],[1.106,0],[0.813,-0.797],[0,-1.139],[-0.798,-0.797],[0,0],[0,0],[0,0],[1.106,0],[0.813,-0.83],[0,-1.106],[-0.83,-0.813],[0,0],[-1.14,0]],"v":[[11.206,-63.672],[10.01,-60.693],[11.206,-57.813],[14.111,-56.592],[26.709,-56.592],[26.709,-8.203],[14.111,-8.203],[11.206,-7.007],[10.01,-4.102],[11.206,-1.196],[14.111,0],[47.314,0],[50.195,-1.196],[51.416,-4.102],[50.22,-7.007],[47.314,-8.203],[34.912,-8.203],[34.912,-56.592],[47.314,-56.592],[50.195,-57.837],[51.416,-60.791],[50.171,-63.672],[47.314,-64.893],[14.111,-64.893]],"c":true},"ix":2},"nm":"I","mn":"ADBE Vector Shape - Group","hd":false}],"nm":"I","np":3,"cix":2,"bm":0,"ix":1,"mn":"ADBE Vector Group","hd":false}]},"fFamily":"OCR A Extended"},{"ch":"T","size":18,"style":"Regular","w":60.4,"data":{"shapes":[{"ty":"gr","it":[{"ind":0,"ty":"sh","ix":1,"ks":{"a":0,"k":{"i":[[-0.798,-0.797],[-1.14,0],[-0.798,0.798],[0,1.14],[0,0],[0,0],[0,0],[-0.814,-0.797],[-1.172,0],[-0.814,0.798],[0,1.14],[0,0],[0,0],[0,0],[-0.83,-0.813],[-1.14,0],[-0.814,0.798],[0,1.14],[0,0],[0,0],[0,0]],"o":[[0.797,0.798],[1.139,0],[0.797,-0.797],[0,0],[0,0],[0,0],[0,1.14],[0.813,0.798],[1.106,0],[0.813,-0.797],[0,0],[0,0],[0,0],[0,1.107],[0.83,0.814],[1.106,0],[0.813,-0.797],[0,0],[0,0],[0,0],[0,1.14]],"v":[[11.206,-50.806],[14.111,-49.609],[17.017,-50.806],[18.213,-53.711],[18.213,-56.592],[26.514,-56.592],[26.514,-4.102],[27.734,-1.196],[30.713,0],[33.594,-1.196],[34.814,-4.102],[34.814,-56.592],[43.115,-56.592],[43.115,-53.613],[44.36,-50.732],[47.314,-49.512],[50.195,-50.708],[51.416,-53.613],[51.416,-64.795],[10.01,-64.795],[10.01,-53.711]],"c":true},"ix":2},"nm":"T","mn":"ADBE Vector Shape - Group","hd":false}],"nm":"T","np":3,"cix":2,"bm":0,"ix":1,"mn":"ADBE Vector Group","hd":false}]},"fFamily":"OCR A Extended"},{"ch":"U","size":18,"style":"Regular","w":60.4,"data":{"shapes":[{"ty":"gr","it":[{"ind":0,"ty":"sh","ix":1,"ks":{"a":0,"k":{"i":[[-2.409,-2.409],[-3.386,0],[0,0],[-2.425,2.441],[0,3.386],[0,0],[0.797,0.814],[1.139,0],[0.797,-0.813],[0,-1.172],[0,0],[0.797,-0.781],[1.139,0],[0,0],[0.813,0.798],[0,1.074],[0,0],[0.813,0.814],[1.106,0],[0.813,-0.83],[0,-1.139],[0,0]],"o":[[2.409,2.409],[0,0],[3.352,0],[2.425,-2.441],[0,0],[0,-1.172],[-0.798,-0.813],[-1.14,0],[-0.798,0.814],[0,0],[0,1.107],[-0.798,0.781],[0,0],[-1.107,0],[-0.814,-0.797],[0,0],[0,-1.106],[-0.814,-0.813],[-1.107,0],[-0.814,0.83],[0,0],[0,3.386]],"v":[[13.623,-3.613],[22.314,0],[39.111,0],[47.778,-3.662],[51.416,-12.402],[51.416,-60.693],[50.22,-63.672],[47.314,-64.893],[44.409,-63.672],[43.213,-60.693],[43.213,-12.305],[42.017,-9.473],[39.111,-8.301],[22.314,-8.301],[19.434,-9.497],[18.213,-12.305],[18.213,-60.791],[16.992,-63.672],[14.111,-64.893],[11.23,-63.647],[10.01,-60.693],[10.01,-12.305]],"c":true},"ix":2},"nm":"U","mn":"ADBE Vector Shape - Group","hd":false}],"nm":"U","np":3,"cix":2,"bm":0,"ix":1,"mn":"ADBE Vector Group","hd":false}]},"fFamily":"OCR A Extended"}]}